safe_pfl_distance/__init__.py
safe_pfl_distance/distance.py
safe_pfl_distance/nets/__init__.py
safe_pfl_distance/nets/alex_net.py
safe_pfl_distance/nets/cnn_net.py
safe_pfl_distance/nets/google_net.py
safe_pfl_distance/nets/res_net.py
safe_pfl_distance/nets/vgg_net.py
safe_pfl_distance/utils/__init__.py
safe_pfl_distance/utils/coordinate_based.py
safe_pfl_distance/utils/cosine.py
safe_pfl_distance/utils/euclidean.py
safe_pfl_distance/utils/jensen_shannon.py
safe_pfl_distance/utils/model_loader.py
safe_pfl_distance/utils/results.py
safe_pfl_distance/utils/wasserstein.py
safe_pfl_distance-0.1.4.dist-info/LICENSE
safe_pfl_distance-0.1.4.dist-info/METADATA
safe_pfl_distance-0.1.4.dist-info/WHEEL
safe_pfl_distance-0.1.4.dist-info/top_level.txt
safe_pfl_distance-0.1.4.dist-info/RECORD
