Metadata-Version: 2.1
Name: safe-pfl-distance
Version: 0.1.4
Summary: safe-pfl distance calculator
Home-page: https://github.com/safe-pfl/distances
Author: MohammadMojtaba Roshani
Author-email: mohammadmojtabaroshani@outlook.com
License: Apache Software License
Classifier: Development Status :: 3 - Alpha
Classifier: Intended Audience :: Science/Research
Classifier: License :: OSI Approved :: Apache Software License
Classifier: Programming Language :: Python :: 3.10
Classifier: Programming Language :: Python :: 3.11
Classifier: Programming Language :: Python :: 3.12
Classifier: Programming Language :: Python :: 3.13
Classifier: Programming Language :: Python :: 3.14
License-File: LICENSE
Requires-Dist: torch >=2.5
Requires-Dist: matplotlib ==3.6.3
Requires-Dist: matplotlib-inline ==0.1.7
Requires-Dist: matplotlib2tikz ==0.7.6
Requires-Dist: scipy >=1.14
Requires-Dist: scikit-learn >=1.5
Requires-Dist: numpy >=2.0
